rsnaped/__init__.py
rsnaped/rsnaped.py
rsnaped-0.1.0.dist-info/LICENSE
rsnaped-0.1.0.dist-info/METADATA
rsnaped-0.1.0.dist-info/WHEEL
rsnaped-0.1.0.dist-info/top_level.txt
rsnaped-0.1.0.dist-info/RECORD
