Metadata-Version: 2.1
Name: rsnaped
Version: 0.1.0
Summary: Python module for single-molecule image processing.
Home-page: https://github.com/MunskyGroup/rsnaped
Author: Luis Aguilera, William Raymond, Brooke Silagy, Brian Munsky
Author-email: luisubald@gmail.com
License: MIT
Keywords: single-molecule image processing
Platform: UNKNOWN
Classifier: Development Status :: 2 - Pre-Alpha
Classifier: Topic :: Scientific/Engineering :: Bio-Informatics
Classifier: Topic :: Scientific/Engineering :: Image Processing
Classifier: License :: OSI Approved :: MIT License
Classifier: Programming Language :: Python :: 3.8
Requires-Python: >=3.8
Requires-Dist: numpy (>=1.20.0)
Requires-Dist: psutil (>=5.3.0)
Requires-Dist: future (>=0.18.0)
Requires-Dist: scikit-image (>=0.18.1)
Requires-Dist: joblib (>=1.0.1)
Requires-Dist: pandas (>=1.2.2)
Requires-Dist: bqplot (>=0.12.21)
Requires-Dist: trackpy (>=0.5.0)
Requires-Dist: ipywidgets (>=7.6.3)
Requires-Dist: numba (>=0.52.0)
Requires-Dist: tifffile (>=2021.2.1)
Requires-Dist: scipy (>=1.6.0)
Requires-Dist: llvmlite (>=0.35.0)
Requires-Dist: torch (>=1.7.1)
Requires-Dist: natsort (>=7.1.1)
Requires-Dist: tqdm (>=4.56.2)
Requires-Dist: matplotlib (>=3.2.2)
Requires-Dist: imageio (>=2.9.0)
Requires-Dist: snapgene-reader (>=0.1.18)
Requires-Dist: cellpose (>=2.0.5)
Requires-Dist: rsnapsim-ssa-cpp (>=0.0.20)
Requires-Dist: rsnapsim (>=0.0.47)
Requires-Dist: croparray (>=0.0.8)
Requires-Dist: seaborn (>=0.11.2)
Requires-Dist: opencv-python (>=4.5.5)
Requires-Dist: ipympl (==0.9.1)
